{"type":"FeatureCollection","features":[{"type":"Feature","geometry":{"type":"MultiPolygon","coordinates":[[[[-76.3695448852265,45.47285223956579,0],[-76.3694825516685,45.49984754633522,0],[-76.4025391150125,45.49988051705041,0],[-76.3931434253637,45.47650273481049,0],[-76.392715466729,45.47533422769429,0],[-76.39178679100321,45.47287548015059,0],[-76.3695448852265,45.47285223956579,0]]]]},"properties":{"fid":213332,"NOM_TUILE":"09_3125037F09_DC","TELECHARGEMENT_TUILE":"https://diffusion.mern.gouv.qc.ca/diffusion/RGQ/Lidar/2009_Pontiac_Lidar_Den1_DonneesClassifiees/Mtm9/Laz/09_3125037F09_DC.LAZ","PROJET":"2009_Pontiac_LiDAR","LICENCE":"Creative Commons Attribution 4.0 International (CC BY 4.0) https://www.donneesquebec.ca/licence","DROIT_AUTEUR":"© Gouvernement du Québec","TYPE_DONNEES":"Données classifiées","DENSITE":"1 pt/m2","CLASSIFICATION":"2,8","PRECISION_PLANIMETRIQUE":"Approximative à 25 cm","PRECISION_ALTIMETRIQUE":"Approximative à 25 cm","PROJECTION":"MTM fuseau 9, NAD83 (SCRS)","SYSREF_ALTIMETRIQUE":"CGVD 1928","CODE_EPSG":"2951","FORMAT":"LAZ (Version 1.2)","DATES_ACQUISITION":"2009-10-19","SAISONS":"Automne","SESSIONS_VOL":"09_701-09_292-1,09_701-09_292-2","CAPTEUR":"Optech ALTM Gemini","TYPE_CAPTEUR":"LiDAR aéroporté","AERONEF":"Piper Aztec (PA-23-250)","ENR_AERONEF":"C-GNZQ","TYPE_AERONEF":"Avion bimoteur","TAILLE_MO":"18.6","UUID":"b5d919b0efa54264a88181569410d95d","NO_SEQ":1337288,"PLUS_RECENTE":"Oui","DATE_INDEX":"2026-03-07","product":"mnt","tile_id":"09_3125037F09_DC","url":"https://diffusion.mern.gouv.qc.ca/diffusion/RGQ/Lidar/2009_Pontiac_Lidar_Den1_DonneesClassifiees/Mtm9/Laz/09_3125037F09_DC.LAZ","provider":"QC"}},{"type":"Feature","geometry":{"type":"MultiPolygon","coordinates":[[[[-76.3694825516685,45.49984754633522,0],[-76.3694200892359,45.52684268314362,0],[-76.4078259013776,45.526880125873234,0],[-76.4078496608202,45.51232971122168,0],[-76.4065114285837,45.511860610927975,0],[-76.4045281511837,45.5048268673918,0],[-76.4025391150125,45.49988051705041,0],[-76.3694825516685,45.49984754633522,0]]]]},"properties":{"fid":213333,"NOM_TUILE":"09_3125040F09_DB","TELECHARGEMENT_TUILE":"https://diffusion.mern.gouv.qc.ca/diffusion/RGQ/Lidar/2009_Pontiac_Lidar_Den1_DonneesBrutes/Mtm9/Laz/09_3125040F09_DB.LAZ","PROJET":"2009_Pontiac_LiDAR","LICENCE":"Creative Commons Attribution 4.0 International (CC BY 4.0) https://www.donneesquebec.ca/licence","DROIT_AUTEUR":"© Gouvernement du Québec","TYPE_DONNEES":"Données brutes","DENSITE":"1 pt/m2","CLASSIFICATION":"0","PRECISION_PLANIMETRIQUE":"Approximative à 25 cm","PRECISION_ALTIMETRIQUE":"Approximative à 25 cm","PROJECTION":"MTM fuseau 9, NAD83 (SCRS)","SYSREF_ALTIMETRIQUE":"CGVD 1928","CODE_EPSG":"2951","FORMAT":"LAZ (Version 1.2)","DATES_ACQUISITION":"2009-10-19","SAISONS":"Automne","SESSIONS_VOL":"09_701-09_292-1,09_701-09_292-2","CAPTEUR":"Optech ALTM Gemini","TYPE_CAPTEUR":"LiDAR aéroporté","AERONEF":"Piper Aztec (PA-23-250)","ENR_AERONEF":"C-GNZQ","TYPE_AERONEF":"Avion bimoteur","TAILLE_MO":"67.0","UUID":"6e301fd481fb49cf84b031b5c7dd7ea0","NO_SEQ":1337289,"PLUS_RECENTE":"Non","DATE_INDEX":"2026-03-07","product":"mnt","tile_id":"09_3125040F09_DB","url":"https://diffusion.mern.gouv.qc.ca/diffusion/RGQ/Lidar/2009_Pontiac_Lidar_Den1_DonneesBrutes/Mtm9/Laz/09_3125040F09_DB.LAZ","provider":"QC"}},{"type":"Feature","geometry":{"type":"MultiPolygon","coordinates":[[[[-76.3311758206073,45.47280198309598,0],[-76.3310952117541,45.499797217076704,0],[-76.3694825516685,45.49984754633522,0],[-76.3695448852265,45.47285223956579,0],[-76.3311758206073,45.47280198309598,0]]]]},"properties":{"fid":213337,"NOM_TUILE":"09_3155037F09_DC","TELECHARGEMENT_TUILE":"https://diffusion.mern.gouv.qc.ca/diffusion/RGQ/Lidar/2009_Pontiac_Lidar_Den1_DonneesClassifiees/Mtm9/Laz/09_3155037F09_DC.LAZ","PROJET":"2009_Pontiac_LiDAR","LICENCE":"Creative Commons Attribution 4.0 International (CC BY 4.0) https://www.donneesquebec.ca/licence","DROIT_AUTEUR":"© Gouvernement du Québec","TYPE_DONNEES":"Données classifiées","DENSITE":"1 pt/m2","CLASSIFICATION":"2,8","PRECISION_PLANIMETRIQUE":"Approximative à 25 cm","PRECISION_ALTIMETRIQUE":"Approximative à 25 cm","PROJECTION":"MTM fuseau 9, NAD83 (SCRS)","SYSREF_ALTIMETRIQUE":"CGVD 1928","CODE_EPSG":"2951","FORMAT":"LAZ (Version 1.2)","DATES_ACQUISITION":"2009-10-19","SAISONS":"Automne","SESSIONS_VOL":"09_701-09_292-1,09_701-09_292-2","CAPTEUR":"Optech ALTM Gemini","TYPE_CAPTEUR":"LiDAR aéroporté","AERONEF":"Piper Aztec (PA-23-250)","ENR_AERONEF":"C-GNZQ","TYPE_AERONEF":"Avion bimoteur","TAILLE_MO":"30.7","UUID":"1a043ffcdfd142d493df273366d54b9f","NO_SEQ":1337310,"PLUS_RECENTE":"Oui","DATE_INDEX":"2026-03-07","product":"mnt","tile_id":"09_3155037F09_DC","url":"https://diffusion.mern.gouv.qc.ca/diffusion/RGQ/Lidar/2009_Pontiac_Lidar_Den1_DonneesClassifiees/Mtm9/Laz/09_3155037F09_DC.LAZ","provider":"QC"}},{"type":"Feature","geometry":{"type":"MultiPolygon","coordinates":[[[[-76.3311887541226,45.46847030959881,0],[-76.3202354598651,45.46830892974221,0],[-76.3059498001984,45.46422875868641,0],[-76.2948695421604,45.4666783295797,0],[-76.2928291237335,45.46687785981761,0],[-76.2928076649553,45.47273881650199,0],[-76.3311758206073,45.47280198309598,0],[-76.3311887541226,45.46847030959881,0]]]]},"properties":{"fid":213346,"NOM_TUILE":"09_3185034F09_DB","TELECHARGEMENT_TUILE":"https://diffusion.mern.gouv.qc.ca/diffusion/RGQ/Lidar/2009_Pontiac_Lidar_Den1_DonneesBrutes/Mtm9/Laz/09_3185034F09_DB.LAZ","PROJET":"2009_Pontiac_LiDAR","LICENCE":"Creative Commons Attribution 4.0 International (CC BY 4.0) https://www.donneesquebec.ca/licence","DROIT_AUTEUR":"© Gouvernement du Québec","TYPE_DONNEES":"Données brutes","DENSITE":"1 pt/m2","CLASSIFICATION":"0","PRECISION_PLANIMETRIQUE":"Approximative à 25 cm","PRECISION_ALTIMETRIQUE":"Approximative à 25 cm","PROJECTION":"MTM fuseau 9, NAD83 (SCRS)","SYSREF_ALTIMETRIQUE":"CGVD 1928","CODE_EPSG":"2951","FORMAT":"LAZ (Version 1.2)","DATES_ACQUISITION":"2009-10-19","SAISONS":"Automne","SESSIONS_VOL":"09_701-09_292-1,09_701-09_292-2","CAPTEUR":"Optech ALTM Gemini","TYPE_CAPTEUR":"LiDAR aéroporté","AERONEF":"Piper Aztec (PA-23-250)","ENR_AERONEF":"C-GNZQ","TYPE_AERONEF":"Avion bimoteur","TAILLE_MO":"18.8","UUID":"03962aef12734d34846635fa4592d75d","NO_SEQ":1337329,"PLUS_RECENTE":"Non","DATE_INDEX":"2026-03-07","product":"mnt","tile_id":"09_3185034F09_DB","url":"https://diffusion.mern.gouv.qc.ca/diffusion/RGQ/Lidar/2009_Pontiac_Lidar_Den1_DonneesBrutes/Mtm9/Laz/09_3185034F09_DB.LAZ","provider":"QC"}},{"type":"Feature","geometry":{"type":"MultiPolygon","coordinates":[[[[-76.2928076649553,45.47273881650199,0],[-76.2927086613366,45.49973402541742,0],[-76.3310952117541,45.499797217076704,0],[-76.3311758206073,45.47280198309598,0],[-76.2928076649553,45.47273881650199,0]]]]},"properties":{"fid":213347,"NOM_TUILE":"09_3185037F09_DC","TELECHARGEMENT_TUILE":"https://diffusion.mern.gouv.qc.ca/diffusion/RGQ/Lidar/2009_Pontiac_Lidar_Den1_DonneesClassifiees/Mtm9/Laz/09_3185037F09_DC.LAZ","PROJET":"2009_Pontiac_LiDAR","LICENCE":"Creative Commons Attribution 4.0 International (CC BY 4.0) https://www.donneesquebec.ca/licence","DROIT_AUTEUR":"© Gouvernement du Québec","TYPE_DONNEES":"Données classifiées","DENSITE":"1 pt/m2","CLASSIFICATION":"2,8","PRECISION_PLANIMETRIQUE":"Approximative à 25 cm","PRECISION_ALTIMETRIQUE":"Approximative à 25 cm","PROJECTION":"MTM fuseau 9, NAD83 (SCRS)","SYSREF_ALTIMETRIQUE":"CGVD 1928","CODE_EPSG":"2951","FORMAT":"LAZ (Version 1.2)","DATES_ACQUISITION":"2009-10-19","SAISONS":"Automne","SESSIONS_VOL":"09_701-09_292-1,09_701-09_292-2","CAPTEUR":"Optech ALTM Gemini","TYPE_CAPTEUR":"LiDAR aéroporté","AERONEF":"Piper Aztec (PA-23-250)","ENR_AERONEF":"C-GNZQ","TYPE_AERONEF":"Avion bimoteur","TAILLE_MO":"29.3","UUID":"2aaa9aefc76148c68a255dda11b1be45","NO_SEQ":1337332,"PLUS_RECENTE":"Oui","DATE_INDEX":"2026-03-07","product":"mnt","tile_id":"09_3185037F09_DC","url":"https://diffusion.mern.gouv.qc.ca/diffusion/RGQ/Lidar/2009_Pontiac_Lidar_Den1_DonneesClassifiees/Mtm9/Laz/09_3185037F09_DC.LAZ","provider":"QC"}},{"type":"Feature","geometry":{"type":"MultiPolygon","coordinates":[[[[-76.2927086613366,45.49973402541742,0],[-76.2926095555189,45.52672905939504,0],[-76.3310143990737,45.52679233063194,0],[-76.3310952117541,45.499797217076704,0],[-76.2927086613366,45.49973402541742,0]]]]},"properties":{"fid":213348,"NOM_TUILE":"09_3185040F09_DB","TELECHARGEMENT_TUILE":"https://diffusion.mern.gouv.qc.ca/diffusion/RGQ/Lidar/2009_Pontiac_Lidar_Den1_DonneesBrutes/Mtm9/Laz/09_3185040F09_DB.LAZ","PROJET":"2009_Pontiac_LiDAR","LICENCE":"Creative Commons Attribution 4.0 International (CC BY 4.0) https://www.donneesquebec.ca/licence","DROIT_AUTEUR":"© Gouvernement du Québec","TYPE_DONNEES":"Données brutes","DENSITE":"1 pt/m2","CLASSIFICATION":"0","PRECISION_PLANIMETRIQUE":"Approximative à 25 cm","PRECISION_ALTIMETRIQUE":"Approximative à 25 cm","PROJECTION":"MTM fuseau 9, NAD83 (SCRS)","SYSREF_ALTIMETRIQUE":"CGVD 1928","CODE_EPSG":"2951","FORMAT":"LAZ (Version 1.2)","DATES_ACQUISITION":"2009-10-19,2009-11-13","SAISONS":"Automne","SESSIONS_VOL":"09_701-09_292-1,09_701-09_292-2,09_701-09_317-1","CAPTEUR":"Optech ALTM Gemini","TYPE_CAPTEUR":"LiDAR aéroporté","AERONEF":"Cessna 421,Piper Aztec (PA-23-250)","ENR_AERONEF":"C-GPSZ,C-GNZQ","TYPE_AERONEF":"Avion monomoteur,Avion bimoteur","TAILLE_MO":"80.1","UUID":"6627f9683f34415a96771cfb6957ff7a","NO_SEQ":1337333,"PLUS_RECENTE":"Non","DATE_INDEX":"2026-03-07","product":"mnt","tile_id":"09_3185040F09_DB","url":"https://diffusion.mern.gouv.qc.ca/diffusion/RGQ/Lidar/2009_Pontiac_Lidar_Den1_DonneesBrutes/Mtm9/Laz/09_3185040F09_DB.LAZ","provider":"QC"}},{"type":"Feature","geometry":{"type":"MultiPolygon","coordinates":[[[[-76.2927086613366,45.49973402541742,0],[-76.2926095555189,45.52672905939504,0],[-76.3310143990737,45.52679233063194,0],[-76.3310952117541,45.499797217076704,0],[-76.2927086613366,45.49973402541742,0]]]]},"properties":{"fid":213349,"NOM_TUILE":"09_3185040F09_DC","TELECHARGEMENT_TUILE":"https://diffusion.mern.gouv.qc.ca/diffusion/RGQ/Lidar/2009_Pontiac_Lidar_Den1_DonneesClassifiees/Mtm9/Laz/09_3185040F09_DC.LAZ","PROJET":"2009_Pontiac_LiDAR","LICENCE":"Creative Commons Attribution 4.0 International (CC BY 4.0) https://www.donneesquebec.ca/licence","DROIT_AUTEUR":"© Gouvernement du Québec","TYPE_DONNEES":"Données classifiées","DENSITE":"1 pt/m2","CLASSIFICATION":"2,8","PRECISION_PLANIMETRIQUE":"Approximative à 25 cm","PRECISION_ALTIMETRIQUE":"Approximative à 25 cm","PROJECTION":"MTM fuseau 9, NAD83 (SCRS)","SYSREF_ALTIMETRIQUE":"CGVD 1928","CODE_EPSG":"2951","FORMAT":"LAZ (Version 1.2)","DATES_ACQUISITION":"2009-10-19,2009-11-13","SAISONS":"Automne","SESSIONS_VOL":"09_701-09_292-1,09_701-09_292-2,09_701-09_317-1","CAPTEUR":"Optech ALTM Gemini","TYPE_CAPTEUR":"LiDAR aéroporté","AERONEF":"Cessna 421,Piper Aztec (PA-23-250)","ENR_AERONEF":"C-GPSZ,C-GNZQ","TYPE_AERONEF":"Avion monomoteur,Avion bimoteur","TAILLE_MO":"25.4","UUID":"8ec1e098fa4e4b3a82dc7729a16f6942","NO_SEQ":1337334,"PLUS_RECENTE":"Oui","DATE_INDEX":"2026-03-07","product":"mnt","tile_id":"09_3185040F09_DC","url":"https://diffusion.mern.gouv.qc.ca/diffusion/RGQ/Lidar/2009_Pontiac_Lidar_Den1_DonneesClassifiees/Mtm9/Laz/09_3185040F09_DC.LAZ","provider":"QC"}},{"type":"Feature","geometry":{"type":"MultiPolygon","coordinates":[[[[-76.2543208512704,45.49965790435592,0],[-76.2542033951581,45.526652901569335,0],[-76.29260884939981,45.526729068447125,0],[-76.292707948651,45.49973398979552,0],[-76.2543208512704,45.49965790435592,0]]]]},"properties":{"fid":213357,"NOM_TUILE":"09_3215040F09_DC","TELECHARGEMENT_TUILE":"https://diffusion.mern.gouv.qc.ca/diffusion/RGQ/Lidar/2009_Collinesoutaouais_Lidar_Den1_DonneesClassifiees/Mtm9/Laz/09_3215040F09_DC.LAZ","PROJET":"2009_CollinesOutaouais_LiDAR","LICENCE":"Creative Commons Attribution 4.0 International (CC BY 4.0) https://www.donneesquebec.ca/licence","DROIT_AUTEUR":"© Gouvernement du Québec","TYPE_DONNEES":"Données classifiées","DENSITE":"1 pt/m2","CLASSIFICATION":"2","PRECISION_PLANIMETRIQUE":"Approximative à 25 cm","PRECISION_ALTIMETRIQUE":"Approximative à 25 cm","PROJECTION":"MTM fuseau 9, NAD83 (SCRS)","SYSREF_ALTIMETRIQUE":"CGVD 1928","CODE_EPSG":"2951","FORMAT":"LAZ (Version 1.1)","DATES_ACQUISITION":"2009-10-19,2009-11-13","SAISONS":"Automne","SESSIONS_VOL":"09_701-09_292-1A,09_701-09_292-2A,09_701-09_317-1A","CAPTEUR":"Optech ALTM Gemini","TYPE_CAPTEUR":"LiDAR aéroporté","AERONEF":"Cessna 421,Piper Aztec (PA-23-250)","ENR_AERONEF":"C-GPSZ,C-GNZQ","TYPE_AERONEF":"Avion monomoteur,Avion bimoteur","TAILLE_MO":"22.7","UUID":"1669b2d8fd2c4cdeb95aaf279a980a8e","NO_SEQ":1337432,"PLUS_RECENTE":"Oui","DATE_INDEX":"2026-03-07","product":"mnt","tile_id":"09_3215040F09_DC","url":"https://diffusion.mern.gouv.qc.ca/diffusion/RGQ/Lidar/2009_Collinesoutaouais_Lidar_Den1_DonneesClassifiees/Mtm9/Laz/09_3215040F09_DC.LAZ","provider":"QC"}},{"type":"Feature","geometry":{"type":"MultiPolygon","coordinates":[[[[-76.3310952117541,45.499797217076704,0],[-76.3310143990737,45.52679233063194,0],[-76.3694200892359,45.52684268314362,0],[-76.3694825516685,45.49984754633522,0],[-76.3310952117541,45.499797217076704,0]]]]},"properties":{"fid":338204,"NOM_TUILE":"09_3155040F09_DB","TELECHARGEMENT_TUILE":"https://diffusion.mern.gouv.qc.ca/diffusion/RGQ/Lidar/2009_Pontiac_Lidar_Den1_DonneesBrutes/Mtm9/Laz/09_3155040F09_DB.LAZ","PROJET":"2009_Pontiac_LiDAR","LICENCE":"Creative Commons Attribution 4.0 International (CC BY 4.0) https://www.donneesquebec.ca/licence","DROIT_AUTEUR":"© Gouvernement du Québec","TYPE_DONNEES":"Données brutes","DENSITE":"1 pt/m2","CLASSIFICATION":"0","PRECISION_PLANIMETRIQUE":"Approximative à 25 cm","PRECISION_ALTIMETRIQUE":"Approximative à 25 cm","PROJECTION":"MTM fuseau 9, NAD83 (SCRS)","SYSREF_ALTIMETRIQUE":"CGVD 1928","CODE_EPSG":"2951","FORMAT":"LAZ (Version 1.2)","DATES_ACQUISITION":"2009-10-19,2009-11-13","SAISONS":"Automne","SESSIONS_VOL":"09_701-09_292-1,09_701-09_292-2,09_701-09_317-1","CAPTEUR":"Optech ALTM Gemini","TYPE_CAPTEUR":"LiDAR aéroporté","AERONEF":"Cessna 421,Piper Aztec (PA-23-250)","ENR_AERONEF":"C-GPSZ,C-GNZQ","TYPE_AERONEF":"Avion monomoteur,Avion bimoteur","TAILLE_MO":"70.3","UUID":"3e576e33117c413f807316955654cd37","NO_SEQ":1337311,"PLUS_RECENTE":"Non","DATE_INDEX":"2026-03-07","product":"mnt","tile_id":"09_3155040F09_DB","url":"https://diffusion.mern.gouv.qc.ca/diffusion/RGQ/Lidar/2009_Pontiac_Lidar_Den1_DonneesBrutes/Mtm9/Laz/09_3155040F09_DB.LAZ","provider":"QC"}},{"type":"Feature","geometry":{"type":"MultiPolygon","coordinates":[[[[-76.2543208512704,45.49965790435592,0],[-76.2542033951581,45.526652901569335,0],[-76.29260884939981,45.526729068447125,0],[-76.292707948651,45.49973398979552,0],[-76.2543208512704,45.49965790435592,0]]]]},"properties":{"fid":338216,"NOM_TUILE":"09_3215040F09_DB","TELECHARGEMENT_TUILE":"https://diffusion.mern.gouv.qc.ca/diffusion/RGQ/Lidar/2009_Collinesoutaouais_Lidar_Den1_DonneesBrutes/Mtm9/Laz/09_3215040F09_DB.LAZ","PROJET":"2009_CollinesOutaouais_LiDAR","LICENCE":"Creative Commons Attribution 4.0 International (CC BY 4.0) https://www.donneesquebec.ca/licence","DROIT_AUTEUR":"© Gouvernement du Québec","TYPE_DONNEES":"Données brutes","DENSITE":"1 pt/m2","CLASSIFICATION":"0","PRECISION_PLANIMETRIQUE":"Approximative à 25 cm","PRECISION_ALTIMETRIQUE":"Approximative à 25 cm","PROJECTION":"MTM fuseau 9, NAD83 (SCRS)","SYSREF_ALTIMETRIQUE":"CGVD 1928","CODE_EPSG":"2951","FORMAT":"LAZ (Version 1.2)","DATES_ACQUISITION":"2009-10-19,2009-11-13","SAISONS":"Automne","SESSIONS_VOL":"09_701-09_292-1A,09_701-09_292-2A,09_701-09_317-1A","CAPTEUR":"Optech ALTM Gemini","TYPE_CAPTEUR":"LiDAR aéroporté","AERONEF":"Cessna 421,Piper Aztec (PA-23-250)","ENR_AERONEF":"C-GPSZ,C-GNZQ","TYPE_AERONEF":"Avion monomoteur,Avion bimoteur","TAILLE_MO":"49.9","UUID":"4931efa4b3574857a1aa75c57d43fd21","NO_SEQ":1337431,"PLUS_RECENTE":"Non","DATE_INDEX":"2026-03-07","product":"mnt","tile_id":"09_3215040F09_DB","url":"https://diffusion.mern.gouv.qc.ca/diffusion/RGQ/Lidar/2009_Collinesoutaouais_Lidar_Den1_DonneesBrutes/Mtm9/Laz/09_3215040F09_DB.LAZ","provider":"QC"}},{"type":"Feature","geometry":{"type":"MultiPolygon","coordinates":[[[[-76.2544308936573,45.47434742421879,0],[-76.240276042135,45.47401881974158,0],[-76.2379880650824,45.47756499966208,0],[-76.2442741065463,45.482906386695774,0],[-76.2432441981631,45.48734338236504,0],[-76.2434571867015,45.496044842569226,0],[-76.2414302952552,45.4996294289996,0],[-76.2543208512704,45.49965790435592,0],[-76.2544308936573,45.47434742421879,0]]]]},"properties":{"fid":338218,"NOM_TUILE":"09_3245037F09_DB","TELECHARGEMENT_TUILE":"https://diffusion.mern.gouv.qc.ca/diffusion/RGQ/Lidar/2009_Collinesoutaouais_Lidar_Den1_DonneesBrutes/Mtm9/Laz/09_3245037F09_DB.LAZ","PROJET":"2009_CollinesOutaouais_LiDAR","LICENCE":"Creative Commons Attribution 4.0 International (CC BY 4.0) https://www.donneesquebec.ca/licence","DROIT_AUTEUR":"© Gouvernement du Québec","TYPE_DONNEES":"Données brutes","DENSITE":"1 pt/m2","CLASSIFICATION":"0","PRECISION_PLANIMETRIQUE":"Approximative à 25 cm","PRECISION_ALTIMETRIQUE":"Approximative à 25 cm","PROJECTION":"MTM fuseau 9, NAD83 (SCRS)","SYSREF_ALTIMETRIQUE":"CGVD 1928","CODE_EPSG":"2951","FORMAT":"LAZ (Version 1.2)","DATES_ACQUISITION":"2009-10-19","SAISONS":"Automne","SESSIONS_VOL":"09_701-09_292-1A,09_701-09_292-2A","CAPTEUR":"Optech ALTM Gemini","TYPE_CAPTEUR":"LiDAR aéroporté","AERONEF":"Piper Aztec (PA-23-250)","ENR_AERONEF":"C-GNZQ","TYPE_AERONEF":"Avion bimoteur","TAILLE_MO":"15.2","UUID":"4d89b8bea91241ef8a6687d0931ed64e","NO_SEQ":1337445,"PLUS_RECENTE":"Non","DATE_INDEX":"2026-03-07","product":"mnt","tile_id":"09_3245037F09_DB","url":"https://diffusion.mern.gouv.qc.ca/diffusion/RGQ/Lidar/2009_Collinesoutaouais_Lidar_Den1_DonneesBrutes/Mtm9/Laz/09_3245037F09_DB.LAZ","provider":"QC"}},{"type":"Feature","geometry":{"type":"MultiPolygon","coordinates":[[[[-76.2544308936573,45.47434742421879,0],[-76.240276042135,45.47401881974158,0],[-76.2379880650824,45.47756499966208,0],[-76.2442741065463,45.482906386695774,0],[-76.2432441981631,45.48734338236504,0],[-76.2434571867015,45.496044842569226,0],[-76.2414302952552,45.4996294289996,0],[-76.2543208512704,45.49965790435592,0],[-76.2544308936573,45.47434742421879,0]]]]},"properties":{"fid":338232,"NOM_TUILE":"09_3245037F09_DC","TELECHARGEMENT_TUILE":"https://diffusion.mern.gouv.qc.ca/diffusion/RGQ/Lidar/2009_Collinesoutaouais_Lidar_Den1_DonneesClassifiees/Mtm9/Laz/09_3245037F09_DC.LAZ","PROJET":"2009_CollinesOutaouais_LiDAR","LICENCE":"Creative Commons Attribution 4.0 International (CC BY 4.0) https://www.donneesquebec.ca/licence","DROIT_AUTEUR":"© Gouvernement du Québec","TYPE_DONNEES":"Données classifiées","DENSITE":"1 pt/m2","CLASSIFICATION":"2","PRECISION_PLANIMETRIQUE":"Approximative à 25 cm","PRECISION_ALTIMETRIQUE":"Approximative à 25 cm","PROJECTION":"MTM fuseau 9, NAD83 (SCRS)","SYSREF_ALTIMETRIQUE":"CGVD 1928","CODE_EPSG":"2951","FORMAT":"LAZ (Version 1.1)","DATES_ACQUISITION":"2009-10-19","SAISONS":"Automne","SESSIONS_VOL":"09_701-09_292-1A,09_701-09_292-2A","CAPTEUR":"Optech ALTM Gemini","TYPE_CAPTEUR":"LiDAR aéroporté","AERONEF":"Piper Aztec (PA-23-250)","ENR_AERONEF":"C-GNZQ","TYPE_AERONEF":"Avion bimoteur","TAILLE_MO":"5.9","UUID":"079f2821bd4946c2a7ce565a3bb32e69","NO_SEQ":1337446,"PLUS_RECENTE":"Oui","DATE_INDEX":"2026-03-07","product":"mnt","tile_id":"09_3245037F09_DC","url":"https://diffusion.mern.gouv.qc.ca/diffusion/RGQ/Lidar/2009_Collinesoutaouais_Lidar_Den1_DonneesClassifiees/Mtm9/Laz/09_3245037F09_DC.LAZ","provider":"QC"}},{"type":"Feature","geometry":{"type":"MultiPolygon","coordinates":[[[[-76.369566799961,45.46335006477701,0],[-76.3695448852265,45.47285223956579,0],[-76.39178679100321,45.47287548015059,0],[-76.3917149902234,45.47268548419889,0],[-76.3803599837906,45.4653430081551,0],[-76.369566799961,45.46335006477701,0]]]]},"properties":{"fid":452309,"NOM_TUILE":"09_3125034F09_DB","TELECHARGEMENT_TUILE":"https://diffusion.mern.gouv.qc.ca/diffusion/RGQ/Lidar/2009_Pontiac_Lidar_Den1_DonneesBrutes/Mtm9/Laz/09_3125034F09_DB.LAZ","PROJET":"2009_Pontiac_LiDAR","LICENCE":"Creative Commons Attribution 4.0 International (CC BY 4.0) https://www.donneesquebec.ca/licence","DROIT_AUTEUR":"© Gouvernement du Québec","TYPE_DONNEES":"Données brutes","DENSITE":"1 pt/m2","CLASSIFICATION":"0","PRECISION_PLANIMETRIQUE":"Approximative à 25 cm","PRECISION_ALTIMETRIQUE":"Approximative à 25 cm","PROJECTION":"MTM fuseau 9, NAD83 (SCRS)","SYSREF_ALTIMETRIQUE":"CGVD 1928","CODE_EPSG":"2951","FORMAT":"LAZ (Version 1.2)","DATES_ACQUISITION":"2009-10-19","SAISONS":"Automne","SESSIONS_VOL":"09_701-09_292-1","CAPTEUR":"Optech ALTM Gemini","TYPE_CAPTEUR":"LiDAR aéroporté","AERONEF":"Piper Aztec (PA-23-250)","ENR_AERONEF":"C-GNZQ","TYPE_AERONEF":"Avion bimoteur","TAILLE_MO":"8.9","UUID":"19ca6a50d3f544458a58926660e4cf20","NO_SEQ":1337285,"PLUS_RECENTE":"Non","DATE_INDEX":"2026-03-07","product":"mnt","tile_id":"09_3125034F09_DB","url":"https://diffusion.mern.gouv.qc.ca/diffusion/RGQ/Lidar/2009_Pontiac_Lidar_Den1_DonneesBrutes/Mtm9/Laz/09_3125034F09_DB.LAZ","provider":"QC"}},{"type":"Feature","geometry":{"type":"MultiPolygon","coordinates":[[[[-76.369566799961,45.46335006477701,0],[-76.3695448852265,45.47285223956579,0],[-76.39178679100321,45.47287548015059,0],[-76.3917149902234,45.47268548419889,0],[-76.3803599837906,45.4653430081551,0],[-76.369566799961,45.46335006477701,0]]]]},"properties":{"fid":452318,"NOM_TUILE":"09_3125034F09_DC","TELECHARGEMENT_TUILE":"https://diffusion.mern.gouv.qc.ca/diffusion/RGQ/Lidar/2009_Pontiac_Lidar_Den1_DonneesClassifiees/Mtm9/Laz/09_3125034F09_DC.LAZ","PROJET":"2009_Pontiac_LiDAR","LICENCE":"Creative Commons Attribution 4.0 International (CC BY 4.0) https://www.donneesquebec.ca/licence","DROIT_AUTEUR":"© Gouvernement du Québec","TYPE_DONNEES":"Données classifiées","DENSITE":"1 pt/m2","CLASSIFICATION":"2,8","PRECISION_PLANIMETRIQUE":"Approximative à 25 cm","PRECISION_ALTIMETRIQUE":"Approximative à 25 cm","PROJECTION":"MTM fuseau 9, NAD83 (SCRS)","SYSREF_ALTIMETRIQUE":"CGVD 1928","CODE_EPSG":"2951","FORMAT":"LAZ (Version 1.2)","DATES_ACQUISITION":"2009-10-19","SAISONS":"Automne","SESSIONS_VOL":"09_701-09_292-1","CAPTEUR":"Optech ALTM Gemini","TYPE_CAPTEUR":"LiDAR aéroporté","AERONEF":"Piper Aztec (PA-23-250)","ENR_AERONEF":"C-GNZQ","TYPE_AERONEF":"Avion bimoteur","TAILLE_MO":"3.0","UUID":"817643a250f643b1ab6cdc071e2d0a20","NO_SEQ":1337286,"PLUS_RECENTE":"Oui","DATE_INDEX":"2026-03-07","product":"mnt","tile_id":"09_3125034F09_DC","url":"https://diffusion.mern.gouv.qc.ca/diffusion/RGQ/Lidar/2009_Pontiac_Lidar_Den1_DonneesClassifiees/Mtm9/Laz/09_3125034F09_DC.LAZ","provider":"QC"}},{"type":"Feature","geometry":{"type":"MultiPolygon","coordinates":[[[[-76.3310952117541,45.499797217076704,0],[-76.3310143990737,45.52679233063194,0],[-76.3694200892359,45.52684268314362,0],[-76.3694825516685,45.49984754633522,0],[-76.3310952117541,45.499797217076704,0]]]]},"properties":{"fid":452319,"NOM_TUILE":"09_3155040F09_DC","TELECHARGEMENT_TUILE":"https://diffusion.mern.gouv.qc.ca/diffusion/RGQ/Lidar/2009_Pontiac_Lidar_Den1_DonneesClassifiees/Mtm9/Laz/09_3155040F09_DC.LAZ","PROJET":"2009_Pontiac_LiDAR","LICENCE":"Creative Commons Attribution 4.0 International (CC BY 4.0) https://www.donneesquebec.ca/licence","DROIT_AUTEUR":"© Gouvernement du Québec","TYPE_DONNEES":"Données classifiées","DENSITE":"1 pt/m2","CLASSIFICATION":"2,8","PRECISION_PLANIMETRIQUE":"Approximative à 25 cm","PRECISION_ALTIMETRIQUE":"Approximative à 25 cm","PROJECTION":"MTM fuseau 9, NAD83 (SCRS)","SYSREF_ALTIMETRIQUE":"CGVD 1928","CODE_EPSG":"2951","FORMAT":"LAZ (Version 1.2)","DATES_ACQUISITION":"2009-10-19,2009-11-13","SAISONS":"Automne","SESSIONS_VOL":"09_701-09_292-1,09_701-09_292-2,09_701-09_317-1","CAPTEUR":"Optech ALTM Gemini","TYPE_CAPTEUR":"LiDAR aéroporté","AERONEF":"Cessna 421,Piper Aztec (PA-23-250)","ENR_AERONEF":"C-GPSZ,C-GNZQ","TYPE_AERONEF":"Avion monomoteur,Avion bimoteur","TAILLE_MO":"28.4","UUID":"c12108f761b842ef9f93f93b1458ee49","NO_SEQ":1337312,"PLUS_RECENTE":"Oui","DATE_INDEX":"2026-03-07","product":"mnt","tile_id":"09_3155040F09_DC","url":"https://diffusion.mern.gouv.qc.ca/diffusion/RGQ/Lidar/2009_Pontiac_Lidar_Den1_DonneesClassifiees/Mtm9/Laz/09_3155040F09_DC.LAZ","provider":"QC"}},{"type":"Feature","geometry":{"type":"MultiPolygon","coordinates":[[[[-76.3311887541226,45.46847030959881,0],[-76.3311758206073,45.47280198309598,0],[-76.3695448852265,45.47285223956579,0],[-76.369566799961,45.46335006477701,0],[-76.3669095136901,45.46285922487201,0],[-76.3475845572132,45.46126534731502,0],[-76.3375559199653,45.461256590161916,0],[-76.3350551326333,45.4685270218655,0],[-76.3311887541226,45.46847030959881,0]]]]},"properties":{"fid":566119,"NOM_TUILE":"09_3155034F09_DB","TELECHARGEMENT_TUILE":"https://diffusion.mern.gouv.qc.ca/diffusion/RGQ/Lidar/2009_Pontiac_Lidar_Den1_DonneesBrutes/Mtm9/Laz/09_3155034F09_DB.LAZ","PROJET":"2009_Pontiac_LiDAR","LICENCE":"Creative Commons Attribution 4.0 International (CC BY 4.0) https://www.donneesquebec.ca/licence","DROIT_AUTEUR":"© Gouvernement du Québec","TYPE_DONNEES":"Données brutes","DENSITE":"1 pt/m2","CLASSIFICATION":"0","PRECISION_PLANIMETRIQUE":"Approximative à 25 cm","PRECISION_ALTIMETRIQUE":"Approximative à 25 cm","PROJECTION":"MTM fuseau 9, NAD83 (SCRS)","SYSREF_ALTIMETRIQUE":"CGVD 1928","CODE_EPSG":"2951","FORMAT":"LAZ (Version 1.2)","DATES_ACQUISITION":"2009-10-19","SAISONS":"Automne","SESSIONS_VOL":"09_701-09_292-1","CAPTEUR":"Optech ALTM Gemini","TYPE_CAPTEUR":"LiDAR aéroporté","AERONEF":"Piper Aztec (PA-23-250)","ENR_AERONEF":"C-GNZQ","TYPE_AERONEF":"Avion bimoteur","TAILLE_MO":"23.9","UUID":"226b642f90554cd4b1755d005f8a79f4","NO_SEQ":1337307,"PLUS_RECENTE":"Non","DATE_INDEX":"2026-03-07","product":"mnt","tile_id":"09_3155034F09_DB","url":"https://diffusion.mern.gouv.qc.ca/diffusion/RGQ/Lidar/2009_Pontiac_Lidar_Den1_DonneesBrutes/Mtm9/Laz/09_3155034F09_DB.LAZ","provider":"QC"}},{"type":"Feature","geometry":{"type":"MultiPolygon","coordinates":[[[[-76.3694825516685,45.49984754633522,0],[-76.3694200892359,45.52684268314362,0],[-76.4078259013776,45.526880125873234,0],[-76.4078496608202,45.51232971122168,0],[-76.4065114285837,45.511860610927975,0],[-76.4045281511837,45.5048268673918,0],[-76.4025391150125,45.49988051705041,0],[-76.3694825516685,45.49984754633522,0]]]]},"properties":{"fid":566132,"NOM_TUILE":"09_3125040F09_DC","TELECHARGEMENT_TUILE":"https://diffusion.mern.gouv.qc.ca/diffusion/RGQ/Lidar/2009_Pontiac_Lidar_Den1_DonneesClassifiees/Mtm9/Laz/09_3125040F09_DC.LAZ","PROJET":"2009_Pontiac_LiDAR","LICENCE":"Creative Commons Attribution 4.0 International (CC BY 4.0) https://www.donneesquebec.ca/licence","DROIT_AUTEUR":"© Gouvernement du Québec","TYPE_DONNEES":"Données classifiées","DENSITE":"1 pt/m2","CLASSIFICATION":"2,8","PRECISION_PLANIMETRIQUE":"Approximative à 25 cm","PRECISION_ALTIMETRIQUE":"Approximative à 25 cm","PROJECTION":"MTM fuseau 9, NAD83 (SCRS)","SYSREF_ALTIMETRIQUE":"CGVD 1928","CODE_EPSG":"2951","FORMAT":"LAZ (Version 1.2)","DATES_ACQUISITION":"2009-10-19","SAISONS":"Automne","SESSIONS_VOL":"09_701-09_292-1,09_701-09_292-2","CAPTEUR":"Optech ALTM Gemini","TYPE_CAPTEUR":"LiDAR aéroporté","AERONEF":"Piper Aztec (PA-23-250)","ENR_AERONEF":"C-GNZQ","TYPE_AERONEF":"Avion bimoteur","TAILLE_MO":"27.4","UUID":"5b36a665b14940ed881524d62b9fc48e","NO_SEQ":1337290,"PLUS_RECENTE":"Oui","DATE_INDEX":"2026-03-07","product":"mnt","tile_id":"09_3125040F09_DC","url":"https://diffusion.mern.gouv.qc.ca/diffusion/RGQ/Lidar/2009_Pontiac_Lidar_Den1_DonneesClassifiees/Mtm9/Laz/09_3125040F09_DC.LAZ","provider":"QC"}},{"type":"Feature","geometry":{"type":"MultiPolygon","coordinates":[[[[-76.3311887541226,45.46847030959881,0],[-76.3311758206073,45.47280198309598,0],[-76.3695448852265,45.47285223956579,0],[-76.369566799961,45.46335006477701,0],[-76.3669095136901,45.46285922487201,0],[-76.3475845572132,45.46126534731502,0],[-76.3375559199653,45.461256590161916,0],[-76.3350551326333,45.4685270218655,0],[-76.3311887541226,45.46847030959881,0]]]]},"properties":{"fid":566134,"NOM_TUILE":"09_3155034F09_DC","TELECHARGEMENT_TUILE":"https://diffusion.mern.gouv.qc.ca/diffusion/RGQ/Lidar/2009_Pontiac_Lidar_Den1_DonneesClassifiees/Mtm9/Laz/09_3155034F09_DC.LAZ","PROJET":"2009_Pontiac_LiDAR","LICENCE":"Creative Commons Attribution 4.0 International (CC BY 4.0) https://www.donneesquebec.ca/licence","DROIT_AUTEUR":"© Gouvernement du Québec","TYPE_DONNEES":"Données classifiées","DENSITE":"1 pt/m2","CLASSIFICATION":"2,8","PRECISION_PLANIMETRIQUE":"Approximative à 25 cm","PRECISION_ALTIMETRIQUE":"Approximative à 25 cm","PROJECTION":"MTM fuseau 9, NAD83 (SCRS)","SYSREF_ALTIMETRIQUE":"CGVD 1928","CODE_EPSG":"2951","FORMAT":"LAZ (Version 1.2)","DATES_ACQUISITION":"2009-10-19","SAISONS":"Automne","SESSIONS_VOL":"09_701-09_292-1","CAPTEUR":"Optech ALTM Gemini","TYPE_CAPTEUR":"LiDAR aéroporté","AERONEF":"Piper Aztec (PA-23-250)","ENR_AERONEF":"C-GNZQ","TYPE_AERONEF":"Avion bimoteur","TAILLE_MO":"9.8","UUID":"4e37bda9c55a403ab9b94ac2c02dfcd3","NO_SEQ":1337308,"PLUS_RECENTE":"Oui","DATE_INDEX":"2026-03-07","product":"mnt","tile_id":"09_3155034F09_DC","url":"https://diffusion.mern.gouv.qc.ca/diffusion/RGQ/Lidar/2009_Pontiac_Lidar_Den1_DonneesClassifiees/Mtm9/Laz/09_3155034F09_DC.LAZ","provider":"QC"}},{"type":"Feature","geometry":{"type":"MultiPolygon","coordinates":[[[[-76.2158539539862,45.515472695306066,0],[-76.2157981115331,45.526563780538744,0],[-76.2542033951581,45.526652901569335,0],[-76.2543208512704,45.49965790435592,0],[-76.2414302952552,45.4996294289996,0],[-76.2401478536562,45.50189718940311,0],[-76.2388865732558,45.505396554630096,0],[-76.2388688939349,45.5054456859423,0],[-76.2408736590093,45.50882409857459,0],[-76.2365679585483,45.51147781571277,0],[-76.2339057052974,45.51225047769678,0],[-76.230498156142,45.513239333215466,0],[-76.2302396451518,45.51448170691477,0],[-76.2239263139254,45.514289078290766,0],[-76.2171033696728,45.51498265793306,0],[-76.2158539539862,45.515472695306066,0]]]]},"properties":{"fid":566137,"NOM_TUILE":"09_3245040F09_DB","TELECHARGEMENT_TUILE":"https://diffusion.mern.gouv.qc.ca/diffusion/RGQ/Lidar/2009_Collinesoutaouais_Lidar_Den1_DonneesBrutes/Mtm9/Laz/09_3245040F09_DB.LAZ","PROJET":"2009_CollinesOutaouais_LiDAR","LICENCE":"Creative Commons Attribution 4.0 International (CC BY 4.0) https://www.donneesquebec.ca/licence","DROIT_AUTEUR":"© Gouvernement du Québec","TYPE_DONNEES":"Données brutes","DENSITE":"1 pt/m2","CLASSIFICATION":"0","PRECISION_PLANIMETRIQUE":"Approximative à 25 cm","PRECISION_ALTIMETRIQUE":"Approximative à 25 cm","PROJECTION":"MTM fuseau 9, NAD83 (SCRS)","SYSREF_ALTIMETRIQUE":"CGVD 1928","CODE_EPSG":"2951","FORMAT":"LAZ (Version 1.2)","DATES_ACQUISITION":"2009-10-19,2009-11-13","SAISONS":"Automne","SESSIONS_VOL":"09_701-09_292-1A,09_701-09_317-1A","CAPTEUR":"Optech ALTM Gemini","TYPE_CAPTEUR":"LiDAR aéroporté","AERONEF":"Cessna 421,Piper Aztec (PA-23-250)","ENR_AERONEF":"C-GPSZ,C-GNZQ","TYPE_AERONEF":"Avion monomoteur,Avion bimoteur","TAILLE_MO":"37.3","UUID":"d47aff62942f4b6c9400607ddadaa36c","NO_SEQ":1337447,"PLUS_RECENTE":"Non","DATE_INDEX":"2026-03-07","product":"mnt","tile_id":"09_3245040F09_DB","url":"https://diffusion.mern.gouv.qc.ca/diffusion/RGQ/Lidar/2009_Collinesoutaouais_Lidar_Den1_DonneesBrutes/Mtm9/Laz/09_3245040F09_DB.LAZ","provider":"QC"}},{"type":"Feature","geometry":{"type":"MultiPolygon","coordinates":[[[[-76.2544308936573,45.47434742421879,0],[-76.2543208512704,45.49965790435592,0],[-76.292707948651,45.49973398979552,0],[-76.29280695959352,45.472738825554586,0],[-76.2613197584154,45.47267735560499,0],[-76.2571845514846,45.47441114539439,0],[-76.2544308936573,45.47434742421879,0]]]]},"properties":{"fid":566149,"NOM_TUILE":"09_3215037F09_DC","TELECHARGEMENT_TUILE":"https://diffusion.mern.gouv.qc.ca/diffusion/RGQ/Lidar/2009_Collinesoutaouais_Lidar_Den1_DonneesClassifiees/Mtm9/Laz/09_3215037F09_DC.LAZ","PROJET":"2009_CollinesOutaouais_LiDAR","LICENCE":"Creative Commons Attribution 4.0 International (CC BY 4.0) https://www.donneesquebec.ca/licence","DROIT_AUTEUR":"© Gouvernement du Québec","TYPE_DONNEES":"Données classifiées","DENSITE":"1 pt/m2","CLASSIFICATION":"2","PRECISION_PLANIMETRIQUE":"Approximative à 25 cm","PRECISION_ALTIMETRIQUE":"Approximative à 25 cm","PROJECTION":"MTM fuseau 9, NAD83 (SCRS)","SYSREF_ALTIMETRIQUE":"CGVD 1928","CODE_EPSG":"2951","FORMAT":"LAZ (Version 1.1)","DATES_ACQUISITION":"2009-10-19","SAISONS":"Automne","SESSIONS_VOL":"09_701-09_292-1A,09_701-09_292-2A","CAPTEUR":"Optech ALTM Gemini","TYPE_CAPTEUR":"LiDAR aéroporté","AERONEF":"Piper Aztec (PA-23-250)","ENR_AERONEF":"C-GNZQ","TYPE_AERONEF":"Avion bimoteur","TAILLE_MO":"19.6","UUID":"a819832600f84d9b8beeb279e50ecaee","NO_SEQ":1337430,"PLUS_RECENTE":"Oui","DATE_INDEX":"2026-03-07","product":"mnt","tile_id":"09_3215037F09_DC","url":"https://diffusion.mern.gouv.qc.ca/diffusion/RGQ/Lidar/2009_Collinesoutaouais_Lidar_Den1_DonneesClassifiees/Mtm9/Laz/09_3215037F09_DC.LAZ","provider":"QC"}},{"type":"Feature","geometry":{"type":"MultiPolygon","coordinates":[[[[-76.2158539539862,45.515472695306066,0],[-76.2157981115331,45.526563780538744,0],[-76.2542033951581,45.526652901569335,0],[-76.2543208512704,45.49965790435592,0],[-76.2414302952552,45.4996294289996,0],[-76.2401478536562,45.50189718940311,0],[-76.2388865732558,45.505396554630096,0],[-76.2388688939349,45.5054456859423,0],[-76.2408736590093,45.50882409857459,0],[-76.2365679585483,45.51147781571277,0],[-76.2339057052974,45.51225047769678,0],[-76.230498156142,45.513239333215466,0],[-76.2302396451518,45.51448170691477,0],[-76.2239263139254,45.514289078290766,0],[-76.2171033696728,45.51498265793306,0],[-76.2158539539862,45.515472695306066,0]]]]},"properties":{"fid":566152,"NOM_TUILE":"09_3245040F09_DC","TELECHARGEMENT_TUILE":"https://diffusion.mern.gouv.qc.ca/diffusion/RGQ/Lidar/2009_Collinesoutaouais_Lidar_Den1_DonneesClassifiees/Mtm9/Laz/09_3245040F09_DC.LAZ","PROJET":"2009_CollinesOutaouais_LiDAR","LICENCE":"Creative Commons Attribution 4.0 International (CC BY 4.0) https://www.donneesquebec.ca/licence","DROIT_AUTEUR":"© Gouvernement du Québec","TYPE_DONNEES":"Données classifiées","DENSITE":"1 pt/m2","CLASSIFICATION":"2","PRECISION_PLANIMETRIQUE":"Approximative à 25 cm","PRECISION_ALTIMETRIQUE":"Approximative à 25 cm","PROJECTION":"MTM fuseau 9, NAD83 (SCRS)","SYSREF_ALTIMETRIQUE":"CGVD 1928","CODE_EPSG":"2951","FORMAT":"LAZ (Version 1.1)","DATES_ACQUISITION":"2009-10-19,2009-11-13","SAISONS":"Automne","SESSIONS_VOL":"09_701-09_292-1A,09_701-09_317-1A","CAPTEUR":"Optech ALTM Gemini","TYPE_CAPTEUR":"LiDAR aéroporté","AERONEF":"Cessna 421,Piper Aztec (PA-23-250)","ENR_AERONEF":"C-GPSZ,C-GNZQ","TYPE_AERONEF":"Avion monomoteur,Avion bimoteur","TAILLE_MO":"13.8","UUID":"209c16d15724405fb7c441fbaf609095","NO_SEQ":1337448,"PLUS_RECENTE":"Oui","DATE_INDEX":"2026-03-07","product":"mnt","tile_id":"09_3245040F09_DC","url":"https://diffusion.mern.gouv.qc.ca/diffusion/RGQ/Lidar/2009_Collinesoutaouais_Lidar_Den1_DonneesClassifiees/Mtm9/Laz/09_3245040F09_DC.LAZ","provider":"QC"}},{"type":"Feature","geometry":{"type":"MultiPolygon","coordinates":[[[[-76.3311758206073,45.47280198309598,0],[-76.3310952117541,45.499797217076704,0],[-76.3694825516685,45.49984754633522,0],[-76.3695448852265,45.47285223956579,0],[-76.3311758206073,45.47280198309598,0]]]]},"properties":{"fid":680110,"NOM_TUILE":"09_3155037F09_DB","TELECHARGEMENT_TUILE":"https://diffusion.mern.gouv.qc.ca/diffusion/RGQ/Lidar/2009_Pontiac_Lidar_Den1_DonneesBrutes/Mtm9/Laz/09_3155037F09_DB.LAZ","PROJET":"2009_Pontiac_LiDAR","LICENCE":"Creative Commons Attribution 4.0 International (CC BY 4.0) https://www.donneesquebec.ca/licence","DROIT_AUTEUR":"© Gouvernement du Québec","TYPE_DONNEES":"Données brutes","DENSITE":"1 pt/m2","CLASSIFICATION":"0","PRECISION_PLANIMETRIQUE":"Approximative à 25 cm","PRECISION_ALTIMETRIQUE":"Approximative à 25 cm","PROJECTION":"MTM fuseau 9, NAD83 (SCRS)","SYSREF_ALTIMETRIQUE":"CGVD 1928","CODE_EPSG":"2951","FORMAT":"LAZ (Version 1.2)","DATES_ACQUISITION":"2009-10-19","SAISONS":"Automne","SESSIONS_VOL":"09_701-09_292-1,09_701-09_292-2","CAPTEUR":"Optech ALTM Gemini","TYPE_CAPTEUR":"LiDAR aéroporté","AERONEF":"Piper Aztec (PA-23-250)","ENR_AERONEF":"C-GNZQ","TYPE_AERONEF":"Avion bimoteur","TAILLE_MO":"80.9","UUID":"955b85a0c08c47ac80ffc3eea398d114","NO_SEQ":1337309,"PLUS_RECENTE":"Non","DATE_INDEX":"2026-03-07","product":"mnt","tile_id":"09_3155037F09_DB","url":"https://diffusion.mern.gouv.qc.ca/diffusion/RGQ/Lidar/2009_Pontiac_Lidar_Den1_DonneesBrutes/Mtm9/Laz/09_3155037F09_DB.LAZ","provider":"QC"}},{"type":"Feature","geometry":{"type":"MultiPolygon","coordinates":[[[[-76.2928076649553,45.47273881650199,0],[-76.2927086613366,45.49973402541742,0],[-76.3310952117541,45.499797217076704,0],[-76.3311758206073,45.47280198309598,0],[-76.2928076649553,45.47273881650199,0]]]]},"properties":{"fid":680111,"NOM_TUILE":"09_3185037F09_DB","TELECHARGEMENT_TUILE":"https://diffusion.mern.gouv.qc.ca/diffusion/RGQ/Lidar/2009_Pontiac_Lidar_Den1_DonneesBrutes/Mtm9/Laz/09_3185037F09_DB.LAZ","PROJET":"2009_Pontiac_LiDAR","LICENCE":"Creative Commons Attribution 4.0 International (CC BY 4.0) https://www.donneesquebec.ca/licence","DROIT_AUTEUR":"© Gouvernement du Québec","TYPE_DONNEES":"Données brutes","DENSITE":"1 pt/m2","CLASSIFICATION":"0","PRECISION_PLANIMETRIQUE":"Approximative à 25 cm","PRECISION_ALTIMETRIQUE":"Approximative à 25 cm","PROJECTION":"MTM fuseau 9, NAD83 (SCRS)","SYSREF_ALTIMETRIQUE":"CGVD 1928","CODE_EPSG":"2951","FORMAT":"LAZ (Version 1.2)","DATES_ACQUISITION":"2009-10-19","SAISONS":"Automne","SESSIONS_VOL":"09_701-09_292-1,09_701-09_292-2","CAPTEUR":"Optech ALTM Gemini","TYPE_CAPTEUR":"LiDAR aéroporté","AERONEF":"Piper Aztec (PA-23-250)","ENR_AERONEF":"C-GNZQ","TYPE_AERONEF":"Avion bimoteur","TAILLE_MO":"95.4","UUID":"79f6477cf5914536a2f56b89d95fea53","NO_SEQ":1337331,"PLUS_RECENTE":"Non","DATE_INDEX":"2026-03-07","product":"mnt","tile_id":"09_3185037F09_DB","url":"https://diffusion.mern.gouv.qc.ca/diffusion/RGQ/Lidar/2009_Pontiac_Lidar_Den1_DonneesBrutes/Mtm9/Laz/09_3185037F09_DB.LAZ","provider":"QC"}},{"type":"Feature","geometry":{"type":"MultiPolygon","coordinates":[[[[-76.29280695959352,45.472738825554586,0],[-76.2928284890953,45.466858063559606,0],[-76.2799246823477,45.46806464820409,0],[-76.2647695768528,45.47123070427619,0],[-76.2613197584154,45.47267735560499,0],[-76.29280695959352,45.472738825554586,0]]]]},"properties":{"fid":680120,"NOM_TUILE":"09_3215034F09_DB","TELECHARGEMENT_TUILE":"https://diffusion.mern.gouv.qc.ca/diffusion/RGQ/Lidar/2009_Collinesoutaouais_Lidar_Den1_DonneesBrutes/Mtm9/Laz/09_3215034F09_DB.LAZ","PROJET":"2009_CollinesOutaouais_LiDAR","LICENCE":"Creative Commons Attribution 4.0 International (CC BY 4.0) https://www.donneesquebec.ca/licence","DROIT_AUTEUR":"© Gouvernement du Québec","TYPE_DONNEES":"Données brutes","DENSITE":"1 pt/m2","CLASSIFICATION":"0","PRECISION_PLANIMETRIQUE":"Approximative à 25 cm","PRECISION_ALTIMETRIQUE":"Approximative à 25 cm","PROJECTION":"MTM fuseau 9, NAD83 (SCRS)","SYSREF_ALTIMETRIQUE":"CGVD 1928","CODE_EPSG":"2951","FORMAT":"LAZ (Version 1.2)","DATES_ACQUISITION":"2009-10-19","SAISONS":"Automne","SESSIONS_VOL":"09_701-09_292-1A,09_701-09_292-2A","CAPTEUR":"Optech ALTM Gemini","TYPE_CAPTEUR":"LiDAR aéroporté","AERONEF":"Piper Aztec (PA-23-250)","ENR_AERONEF":"C-GNZQ","TYPE_AERONEF":"Avion bimoteur","TAILLE_MO":"7.9","UUID":"bf03bf7ed0d447118376e847c486be29","NO_SEQ":1337427,"PLUS_RECENTE":"Non","DATE_INDEX":"2026-03-07","product":"mnt","tile_id":"09_3215034F09_DB","url":"https://diffusion.mern.gouv.qc.ca/diffusion/RGQ/Lidar/2009_Collinesoutaouais_Lidar_Den1_DonneesBrutes/Mtm9/Laz/09_3215034F09_DB.LAZ","provider":"QC"}},{"type":"Feature","geometry":{"type":"MultiPolygon","coordinates":[[[[-76.29280695959352,45.472738825554586,0],[-76.2928284890953,45.466858063559606,0],[-76.2799246823477,45.46806464820409,0],[-76.2647695768528,45.47123070427619,0],[-76.2613197584154,45.47267735560499,0],[-76.29280695959352,45.472738825554586,0]]]]},"properties":{"fid":680141,"NOM_TUILE":"09_3215034F09_DC","TELECHARGEMENT_TUILE":"https://diffusion.mern.gouv.qc.ca/diffusion/RGQ/Lidar/2009_Collinesoutaouais_Lidar_Den1_DonneesClassifiees/Mtm9/Laz/09_3215034F09_DC.LAZ","PROJET":"2009_CollinesOutaouais_LiDAR","LICENCE":"Creative Commons Attribution 4.0 International (CC BY 4.0) https://www.donneesquebec.ca/licence","DROIT_AUTEUR":"© Gouvernement du Québec","TYPE_DONNEES":"Données classifiées","DENSITE":"1 pt/m2","CLASSIFICATION":"2","PRECISION_PLANIMETRIQUE":"Approximative à 25 cm","PRECISION_ALTIMETRIQUE":"Approximative à 25 cm","PROJECTION":"MTM fuseau 9, NAD83 (SCRS)","SYSREF_ALTIMETRIQUE":"CGVD 1928","CODE_EPSG":"2951","FORMAT":"LAZ (Version 1.1)","DATES_ACQUISITION":"2009-10-19","SAISONS":"Automne","SESSIONS_VOL":"09_701-09_292-1A,09_701-09_292-2A","CAPTEUR":"Optech ALTM Gemini","TYPE_CAPTEUR":"LiDAR aéroporté","AERONEF":"Piper Aztec (PA-23-250)","ENR_AERONEF":"C-GNZQ","TYPE_AERONEF":"Avion bimoteur","TAILLE_MO":"2.3","UUID":"61501e236ad34b24ae7fa4e993585417","NO_SEQ":1337428,"PLUS_RECENTE":"Oui","DATE_INDEX":"2026-03-07","product":"mnt","tile_id":"09_3215034F09_DC","url":"https://diffusion.mern.gouv.qc.ca/diffusion/RGQ/Lidar/2009_Collinesoutaouais_Lidar_Den1_DonneesClassifiees/Mtm9/Laz/09_3215034F09_DC.LAZ","provider":"QC"}},{"type":"Feature","geometry":{"type":"MultiPolygon","coordinates":[[[[-76.3695448852265,45.47285223956579,0],[-76.3694825516685,45.49984754633522,0],[-76.4025391150125,45.49988051705041,0],[-76.3931434253637,45.47650273481049,0],[-76.392715466729,45.47533422769429,0],[-76.39178679100321,45.47287548015059,0],[-76.3695448852265,45.47285223956579,0]]]]},"properties":{"fid":794304,"NOM_TUILE":"09_3125037F09_DB","TELECHARGEMENT_TUILE":"https://diffusion.mern.gouv.qc.ca/diffusion/RGQ/Lidar/2009_Pontiac_Lidar_Den1_DonneesBrutes/Mtm9/Laz/09_3125037F09_DB.LAZ","PROJET":"2009_Pontiac_LiDAR","LICENCE":"Creative Commons Attribution 4.0 International (CC BY 4.0) https://www.donneesquebec.ca/licence","DROIT_AUTEUR":"© Gouvernement du Québec","TYPE_DONNEES":"Données brutes","DENSITE":"1 pt/m2","CLASSIFICATION":"0","PRECISION_PLANIMETRIQUE":"Approximative à 25 cm","PRECISION_ALTIMETRIQUE":"Approximative à 25 cm","PROJECTION":"MTM fuseau 9, NAD83 (SCRS)","SYSREF_ALTIMETRIQUE":"CGVD 1928","CODE_EPSG":"2951","FORMAT":"LAZ (Version 1.2)","DATES_ACQUISITION":"2009-10-19","SAISONS":"Automne","SESSIONS_VOL":"09_701-09_292-1,09_701-09_292-2","CAPTEUR":"Optech ALTM Gemini","TYPE_CAPTEUR":"LiDAR aéroporté","AERONEF":"Piper Aztec (PA-23-250)","ENR_AERONEF":"C-GNZQ","TYPE_AERONEF":"Avion bimoteur","TAILLE_MO":"47.7","UUID":"695e6ca51c4848a78a3db23d7023fb3c","NO_SEQ":1337287,"PLUS_RECENTE":"Non","DATE_INDEX":"2026-03-07","product":"mnt","tile_id":"09_3125037F09_DB","url":"https://diffusion.mern.gouv.qc.ca/diffusion/RGQ/Lidar/2009_Pontiac_Lidar_Den1_DonneesBrutes/Mtm9/Laz/09_3125037F09_DB.LAZ","provider":"QC"}},{"type":"Feature","geometry":{"type":"MultiPolygon","coordinates":[[[[-76.3311887541226,45.46847030959881,0],[-76.3202354598651,45.46830892974221,0],[-76.3059498001984,45.46422875868641,0],[-76.2948695421604,45.4666783295797,0],[-76.2928291237335,45.46687785981761,0],[-76.2928076649553,45.47273881650199,0],[-76.3311758206073,45.47280198309598,0],[-76.3311887541226,45.46847030959881,0]]]]},"properties":{"fid":794316,"NOM_TUILE":"09_3185034F09_DC","TELECHARGEMENT_TUILE":"https://diffusion.mern.gouv.qc.ca/diffusion/RGQ/Lidar/2009_Pontiac_Lidar_Den1_DonneesClassifiees/Mtm9/Laz/09_3185034F09_DC.LAZ","PROJET":"2009_Pontiac_LiDAR","LICENCE":"Creative Commons Attribution 4.0 International (CC BY 4.0) https://www.donneesquebec.ca/licence","DROIT_AUTEUR":"© Gouvernement du Québec","TYPE_DONNEES":"Données classifiées","DENSITE":"1 pt/m2","CLASSIFICATION":"2,8","PRECISION_PLANIMETRIQUE":"Approximative à 25 cm","PRECISION_ALTIMETRIQUE":"Approximative à 25 cm","PROJECTION":"MTM fuseau 9, NAD83 (SCRS)","SYSREF_ALTIMETRIQUE":"CGVD 1928","CODE_EPSG":"2951","FORMAT":"LAZ (Version 1.2)","DATES_ACQUISITION":"2009-10-19","SAISONS":"Automne","SESSIONS_VOL":"09_701-09_292-1,09_701-09_292-2","CAPTEUR":"Optech ALTM Gemini","TYPE_CAPTEUR":"LiDAR aéroporté","AERONEF":"Piper Aztec (PA-23-250)","ENR_AERONEF":"C-GNZQ","TYPE_AERONEF":"Avion bimoteur","TAILLE_MO":"6.1","UUID":"447b8b0d66b744dd876c2fe0f4d0af70","NO_SEQ":1337330,"PLUS_RECENTE":"Oui","DATE_INDEX":"2026-03-07","product":"mnt","tile_id":"09_3185034F09_DC","url":"https://diffusion.mern.gouv.qc.ca/diffusion/RGQ/Lidar/2009_Pontiac_Lidar_Den1_DonneesClassifiees/Mtm9/Laz/09_3185034F09_DC.LAZ","provider":"QC"}},{"type":"Feature","geometry":{"type":"MultiPolygon","coordinates":[[[[-76.2544308936573,45.47434742421879,0],[-76.2543208512704,45.49965790435592,0],[-76.292707948651,45.49973398979552,0],[-76.29280695959352,45.472738825554586,0],[-76.2613197584154,45.47267735560499,0],[-76.2571845514846,45.47441114539439,0],[-76.2544308936573,45.47434742421879,0]]]]},"properties":{"fid":908144,"NOM_TUILE":"09_3215037F09_DB","TELECHARGEMENT_TUILE":"https://diffusion.mern.gouv.qc.ca/diffusion/RGQ/Lidar/2009_Collinesoutaouais_Lidar_Den1_DonneesBrutes/Mtm9/Laz/09_3215037F09_DB.LAZ","PROJET":"2009_CollinesOutaouais_LiDAR","LICENCE":"Creative Commons Attribution 4.0 International (CC BY 4.0) https://www.donneesquebec.ca/licence","DROIT_AUTEUR":"© Gouvernement du Québec","TYPE_DONNEES":"Données brutes","DENSITE":"1 pt/m2","CLASSIFICATION":"0","PRECISION_PLANIMETRIQUE":"Approximative à 25 cm","PRECISION_ALTIMETRIQUE":"Approximative à 25 cm","PROJECTION":"MTM fuseau 9, NAD83 (SCRS)","SYSREF_ALTIMETRIQUE":"CGVD 1928","CODE_EPSG":"2951","FORMAT":"LAZ (Version 1.2)","DATES_ACQUISITION":"2009-10-19","SAISONS":"Automne","SESSIONS_VOL":"09_701-09_292-1A,09_701-09_292-2A","CAPTEUR":"Optech ALTM Gemini","TYPE_CAPTEUR":"LiDAR aéroporté","AERONEF":"Piper Aztec (PA-23-250)","ENR_AERONEF":"C-GNZQ","TYPE_AERONEF":"Avion bimoteur","TAILLE_MO":"67.3","UUID":"1f3692b7901b42a48d2714ab6fddc819","NO_SEQ":1337429,"PLUS_RECENTE":"Non","DATE_INDEX":"2026-03-07","product":"mnt","tile_id":"09_3215037F09_DB","url":"https://diffusion.mern.gouv.qc.ca/diffusion/RGQ/Lidar/2009_Collinesoutaouais_Lidar_Den1_DonneesBrutes/Mtm9/Laz/09_3215037F09_DB.LAZ","provider":"QC"}}]}