{"type":"FeatureCollection","features":[{"type":"Feature","geometry":{"type":"MultiPolygon","coordinates":[[[[-73.4467305495534,44.99597495834451,0],[-73.4467222273545,45.00497421301888,0],[-73.4594074038034,45.00497941931219,0],[-73.4594137345772,44.99598019598363,0],[-73.4467305495534,44.99597495834451,0]]]]},"properties":{"fid":130256,"NOM_TUILE":"21_3084984F08_DB","TELECHARGEMENT_TUILE":"https://diffusion.mern.gouv.qc.ca/diffusion/RGQ/Lidar/2021_Monteregiesudest_Lidar_Den10_DonneesBrutes/Mtm8/Laz/21_3084984F08_DB.LAZ","PROJET":"2021_Montérégie Sud-Est_Lidar","LICENCE":"Creative Commons Attribution 4.0 International (CC BY 4.0) https://www.donneesquebec.ca/licence","DROIT_AUTEUR":"© Gouvernement du Québec","TYPE_DONNEES":"Données brutes","DENSITE":"10 pts/m2","CLASSIFICATION":"0","PRECISION_PLANIMETRIQUE":"Approximative à 15 cm","PRECISION_ALTIMETRIQUE":"Approximative à 15 cm","PROJECTION":"MTM fuseau 8, NAD83 (SCRS)","SYSREF_ALTIMETRIQUE":"CGVD 1928","CODE_EPSG":"2950","FORMAT":"LAZ (Version 1.2)","DATES_ACQUISITION":"2021-10-23,2021-11-06","SAISONS":"Automne","SESSIONS_VOL":"21_600021-38_296-1,21_600021-38_310-2","CAPTEUR":"Optech ALTM Galaxy","TYPE_CAPTEUR":"LiDAR aéroporté","AERONEF":"Piper Navajo (PA-31)","ENR_AERONEF":"C-FPXL","TYPE_AERONEF":"Avion bimoteur","TAILLE_MO":"26.5","UUID":"87521d9f3e1e40e8819f9afe30446a87","NO_SEQ":870966,"PLUS_RECENTE":"Non","DATE_INDEX":"2026-03-07","product":"lidar","tile_id":"21_3084984F08_DB","url":"https://diffusion.mern.gouv.qc.ca/diffusion/RGQ/Lidar/2021_Monteregiesudest_Lidar_Den10_DonneesBrutes/Mtm8/Laz/21_3084984F08_DB.LAZ","provider":"QC"}},{"type":"Feature","geometry":{"type":"MultiPolygon","coordinates":[[[[-73.408666697031,45.00495010369779,0],[-73.4086810066059,44.99595089082152,0],[-73.3959978485305,44.995940037634526,0],[-73.3959815431829,45.0049392360855,0],[-73.408666697031,45.00495010369779,0]]]]},"properties":{"fid":282784,"NOM_TUILE":"21_3124984F08_DB","TELECHARGEMENT_TUILE":"https://diffusion.mern.gouv.qc.ca/diffusion/RGQ/Lidar/2021_Monteregiesudest_Lidar_Den10_DonneesBrutes/Mtm8/Laz/21_3124984F08_DB.LAZ","PROJET":"2021_Montérégie Sud-Est_Lidar","LICENCE":"Creative Commons Attribution 4.0 International (CC BY 4.0) https://www.donneesquebec.ca/licence","DROIT_AUTEUR":"© Gouvernement du Québec","TYPE_DONNEES":"Données brutes","DENSITE":"10 pts/m2","CLASSIFICATION":"0","PRECISION_PLANIMETRIQUE":"Approximative à 15 cm","PRECISION_ALTIMETRIQUE":"Approximative à 15 cm","PROJECTION":"MTM fuseau 8, NAD83 (SCRS)","SYSREF_ALTIMETRIQUE":"CGVD 1928","CODE_EPSG":"2950","FORMAT":"LAZ (Version 1.2)","DATES_ACQUISITION":"2021-10-23,2021-11-06","SAISONS":"Automne","SESSIONS_VOL":"21_600021-38_296-1,21_600021-38_310-2","CAPTEUR":"Optech ALTM Galaxy","TYPE_CAPTEUR":"LiDAR aéroporté","AERONEF":"Piper Navajo (PA-31)","ENR_AERONEF":"C-FPXL","TYPE_AERONEF":"Avion bimoteur","TAILLE_MO":"51.3","UUID":"4d0a6c4aa97747919f17dd99ceabd6eb","NO_SEQ":871099,"PLUS_RECENTE":"Non","DATE_INDEX":"2026-03-07","product":"lidar","tile_id":"21_3124984F08_DB","url":"https://diffusion.mern.gouv.qc.ca/diffusion/RGQ/Lidar/2021_Monteregiesudest_Lidar_Den10_DonneesBrutes/Mtm8/Laz/21_3124984F08_DB.LAZ","provider":"QC"}},{"type":"Feature","geometry":{"type":"MultiPolygon","coordinates":[[[[-73.4213641870967,44.995960328157025,0],[-73.4213518733061,45.004959555212295,0],[-73.4340370713455,45.00496759062149,0],[-73.4340473893402,44.99596834963353,0],[-73.4213641870967,44.995960328157025,0]]]]},"properties":{"fid":396462,"NOM_TUILE":"21_3104984F08_DB","TELECHARGEMENT_TUILE":"https://diffusion.mern.gouv.qc.ca/diffusion/RGQ/Lidar/2021_Monteregiesudest_Lidar_Den10_DonneesBrutes/Mtm8/Laz/21_3104984F08_DB.LAZ","PROJET":"2021_Montérégie Sud-Est_Lidar","LICENCE":"Creative Commons Attribution 4.0 International (CC BY 4.0) https://www.donneesquebec.ca/licence","DROIT_AUTEUR":"© Gouvernement du Québec","TYPE_DONNEES":"Données brutes","DENSITE":"10 pts/m2","CLASSIFICATION":"0","PRECISION_PLANIMETRIQUE":"Approximative à 15 cm","PRECISION_ALTIMETRIQUE":"Approximative à 15 cm","PROJECTION":"MTM fuseau 8, NAD83 (SCRS)","SYSREF_ALTIMETRIQUE":"CGVD 1928","CODE_EPSG":"2950","FORMAT":"LAZ (Version 1.2)","DATES_ACQUISITION":"2021-10-23,2021-11-06","SAISONS":"Automne","SESSIONS_VOL":"21_600021-38_296-1,21_600021-38_310-2","CAPTEUR":"Optech ALTM Galaxy","TYPE_CAPTEUR":"LiDAR aéroporté","AERONEF":"Piper Navajo (PA-31)","ENR_AERONEF":"C-FPXL","TYPE_AERONEF":"Avion bimoteur","TAILLE_MO":"60.8","UUID":"638dc2a322ce494b919eab754fa7189d","NO_SEQ":871032,"PLUS_RECENTE":"Non","DATE_INDEX":"2026-03-07","product":"lidar","tile_id":"21_3104984F08_DB","url":"https://diffusion.mern.gouv.qc.ca/diffusion/RGQ/Lidar/2021_Monteregiesudest_Lidar_Den10_DonneesBrutes/Mtm8/Laz/21_3104984F08_DB.LAZ","provider":"QC"}},{"type":"Feature","geometry":{"type":"MultiPolygon","coordinates":[[[[-73.3706315434541,44.995914131579916,0],[-73.3706112508914,45.00491334523279,0],[-73.38329641674,45.004926997173094,0],[-73.3833146504087,44.99592777166491,0],[-73.3706315434541,44.995914131579916,0]]]]},"properties":{"fid":396471,"NOM_TUILE":"21_3144984F08_DB","TELECHARGEMENT_TUILE":"https://diffusion.mern.gouv.qc.ca/diffusion/RGQ/Lidar/2021_Monteregiesudest_Lidar_Den10_DonneesBrutes/Mtm8/Laz/21_3144984F08_DB.LAZ","PROJET":"2021_Montérégie Sud-Est_Lidar","LICENCE":"Creative Commons Attribution 4.0 International (CC BY 4.0) https://www.donneesquebec.ca/licence","DROIT_AUTEUR":"© Gouvernement du Québec","TYPE_DONNEES":"Données brutes","DENSITE":"10 pts/m2","CLASSIFICATION":"0","PRECISION_PLANIMETRIQUE":"Approximative à 15 cm","PRECISION_ALTIMETRIQUE":"Approximative à 15 cm","PROJECTION":"MTM fuseau 8, NAD83 (SCRS)","SYSREF_ALTIMETRIQUE":"CGVD 1928","CODE_EPSG":"2950","FORMAT":"LAZ (Version 1.2)","DATES_ACQUISITION":"2021-10-23,2021-11-06","SAISONS":"Automne","SESSIONS_VOL":"21_600021-38_296-1,21_600021-38_310-2","CAPTEUR":"Optech ALTM Galaxy","TYPE_CAPTEUR":"LiDAR aéroporté","AERONEF":"Piper Navajo (PA-31)","ENR_AERONEF":"C-FPXL","TYPE_AERONEF":"Avion bimoteur","TAILLE_MO":"37.8","UUID":"297dfc79344341efa063164c8b4f5b2c","NO_SEQ":871165,"PLUS_RECENTE":"Non","DATE_INDEX":"2026-03-07","product":"lidar","tile_id":"21_3144984F08_DB","url":"https://diffusion.mern.gouv.qc.ca/diffusion/RGQ/Lidar/2021_Monteregiesudest_Lidar_Den10_DonneesBrutes/Mtm8/Laz/21_3144984F08_DB.LAZ","provider":"QC"}},{"type":"Feature","geometry":{"type":"MultiPolygon","coordinates":[[[[-73.3579261051419,45.00489823241199,0],[-73.3579483934625,44.99589903392281,0],[-73.3452652096891,44.99588256825802,0],[-73.3452409887512,45.0048817483007,0],[-73.3579261051419,45.00489823241199,0]]]]},"properties":{"fid":396476,"NOM_TUILE":"21_3164984F08_DB","TELECHARGEMENT_TUILE":"https://diffusion.mern.gouv.qc.ca/diffusion/RGQ/Lidar/2021_Monteregiesudest_Lidar_Den10_DonneesBrutes/Mtm8/Laz/21_3164984F08_DB.LAZ","PROJET":"2021_Montérégie Sud-Est_Lidar","LICENCE":"Creative Commons Attribution 4.0 International (CC BY 4.0) https://www.donneesquebec.ca/licence","DROIT_AUTEUR":"© Gouvernement du Québec","TYPE_DONNEES":"Données brutes","DENSITE":"10 pts/m2","CLASSIFICATION":"0","PRECISION_PLANIMETRIQUE":"Approximative à 15 cm","PRECISION_ALTIMETRIQUE":"Approximative à 15 cm","PROJECTION":"MTM fuseau 8, NAD83 (SCRS)","SYSREF_ALTIMETRIQUE":"CGVD 1928","CODE_EPSG":"2950","FORMAT":"LAZ (Version 1.2)","DATES_ACQUISITION":"2021-10-23,2021-11-06","SAISONS":"Automne","SESSIONS_VOL":"21_600021-38_296-1,21_600021-38_310-2","CAPTEUR":"Optech ALTM Galaxy","TYPE_CAPTEUR":"LiDAR aéroporté","AERONEF":"Piper Navajo (PA-31)","ENR_AERONEF":"C-FPXL","TYPE_AERONEF":"Avion bimoteur","TAILLE_MO":"13.8","UUID":"962d95a42b364a748266edf694859475","NO_SEQ":871228,"PLUS_RECENTE":"Non","DATE_INDEX":"2026-03-07","product":"lidar","tile_id":"21_3164984F08_DB","url":"https://diffusion.mern.gouv.qc.ca/diffusion/RGQ/Lidar/2021_Monteregiesudest_Lidar_Den10_DonneesBrutes/Mtm8/Laz/21_3164984F08_DB.LAZ","provider":"QC"}},{"type":"Feature","geometry":{"type":"MultiPolygon","coordinates":[[[[-73.4847801589251,44.995986378871834,0],[-73.4847777522398,45.0049855866827,0],[-73.4974629904474,45.004986589414294,0],[-73.4974633381992,44.99598737202502,0],[-73.4847801589251,44.995986378871834,0]]]]},"properties":{"fid":396485,"NOM_TUILE":"21_3054984F08_DB","TELECHARGEMENT_TUILE":"https://diffusion.mern.gouv.qc.ca/diffusion/RGQ/Lidar/2021_Monteregiesudest_Lidar_Den10_DonneesBrutes/Mtm8/Laz/21_3054984F08_DB.LAZ","PROJET":"2021_Montérégie Sud-Est_Lidar","LICENCE":"Creative Commons Attribution 4.0 International (CC BY 4.0) https://www.donneesquebec.ca/licence","DROIT_AUTEUR":"© Gouvernement du Québec","TYPE_DONNEES":"Données brutes","DENSITE":"10 pts/m2","CLASSIFICATION":"0","PRECISION_PLANIMETRIQUE":"Approximative à 15 cm","PRECISION_ALTIMETRIQUE":"Approximative à 15 cm","PROJECTION":"MTM fuseau 8, NAD83 (SCRS)","SYSREF_ALTIMETRIQUE":"CGVD 1928","CODE_EPSG":"2950","FORMAT":"LAZ (Version 1.2)","DATES_ACQUISITION":"2021-10-23,2021-11-06","SAISONS":"Automne","SESSIONS_VOL":"21_600021-38_296-1,21_600021-38_310-2","CAPTEUR":"Optech ALTM Galaxy","TYPE_CAPTEUR":"LiDAR aéroporté","AERONEF":"Piper Navajo (PA-31)","ENR_AERONEF":"C-FPXL","TYPE_AERONEF":"Avion bimoteur","TAILLE_MO":"44.8","UUID":"5ae9e1d89b444eb598d2ecba67a3b091","NO_SEQ":870867,"PLUS_RECENTE":"Non","DATE_INDEX":"2026-03-07","product":"lidar","tile_id":"21_3054984F08_DB","url":"https://diffusion.mern.gouv.qc.ca/diffusion/RGQ/Lidar/2021_Monteregiesudest_Lidar_Den10_DonneesBrutes/Mtm8/Laz/21_3054984F08_DB.LAZ","provider":"QC"}},{"type":"Feature","geometry":{"type":"MultiPolygon","coordinates":[[[[-73.4467222273545,45.00497421301888,0],[-73.4467305495534,44.99597495834451,0],[-73.4340473893402,44.99596834963353,0],[-73.4340370713455,45.00496759062149,0],[-73.4467222273545,45.00497421301888,0]]]]},"properties":{"fid":624230,"NOM_TUILE":"21_3094984F08_DB","TELECHARGEMENT_TUILE":"https://diffusion.mern.gouv.qc.ca/diffusion/RGQ/Lidar/2021_Monteregiesudest_Lidar_Den10_DonneesBrutes/Mtm8/Laz/21_3094984F08_DB.LAZ","PROJET":"2021_Montérégie Sud-Est_Lidar","LICENCE":"Creative Commons Attribution 4.0 International (CC BY 4.0) https://www.donneesquebec.ca/licence","DROIT_AUTEUR":"© Gouvernement du Québec","TYPE_DONNEES":"Données brutes","DENSITE":"10 pts/m2","CLASSIFICATION":"0","PRECISION_PLANIMETRIQUE":"Approximative à 15 cm","PRECISION_ALTIMETRIQUE":"Approximative à 15 cm","PROJECTION":"MTM fuseau 8, NAD83 (SCRS)","SYSREF_ALTIMETRIQUE":"CGVD 1928","CODE_EPSG":"2950","FORMAT":"LAZ (Version 1.2)","DATES_ACQUISITION":"2021-10-23,2021-11-06","SAISONS":"Automne","SESSIONS_VOL":"21_600021-38_296-1,21_600021-38_310-2","CAPTEUR":"Optech ALTM Galaxy","TYPE_CAPTEUR":"LiDAR aéroporté","AERONEF":"Piper Navajo (PA-31)","ENR_AERONEF":"C-FPXL","TYPE_AERONEF":"Avion bimoteur","TAILLE_MO":"45.9","UUID":"f890221ecee6432ba6c883842033114f","NO_SEQ":870999,"PLUS_RECENTE":"Non","DATE_INDEX":"2026-03-07","product":"lidar","tile_id":"21_3094984F08_DB","url":"https://diffusion.mern.gouv.qc.ca/diffusion/RGQ/Lidar/2021_Monteregiesudest_Lidar_Den10_DonneesBrutes/Mtm8/Laz/21_3094984F08_DB.LAZ","provider":"QC"}},{"type":"Feature","geometry":{"type":"MultiPolygon","coordinates":[[[[-73.4086810066059,44.99595089082152,0],[-73.408666697031,45.00495010369779,0],[-73.4213518733061,45.004959555212295,0],[-73.4213641870967,44.995960328157025,0],[-73.4086810066059,44.99595089082152,0]]]]},"properties":{"fid":624234,"NOM_TUILE":"21_3114984F08_DB","TELECHARGEMENT_TUILE":"https://diffusion.mern.gouv.qc.ca/diffusion/RGQ/Lidar/2021_Monteregiesudest_Lidar_Den10_DonneesBrutes/Mtm8/Laz/21_3114984F08_DB.LAZ","PROJET":"2021_Montérégie Sud-Est_Lidar","LICENCE":"Creative Commons Attribution 4.0 International (CC BY 4.0) https://www.donneesquebec.ca/licence","DROIT_AUTEUR":"© Gouvernement du Québec","TYPE_DONNEES":"Données brutes","DENSITE":"10 pts/m2","CLASSIFICATION":"0","PRECISION_PLANIMETRIQUE":"Approximative à 15 cm","PRECISION_ALTIMETRIQUE":"Approximative à 15 cm","PROJECTION":"MTM fuseau 8, NAD83 (SCRS)","SYSREF_ALTIMETRIQUE":"CGVD 1928","CODE_EPSG":"2950","FORMAT":"LAZ (Version 1.2)","DATES_ACQUISITION":"2021-10-23,2021-11-06","SAISONS":"Automne","SESSIONS_VOL":"21_600021-38_296-1,21_600021-38_310-2","CAPTEUR":"Optech ALTM Galaxy","TYPE_CAPTEUR":"LiDAR aéroporté","AERONEF":"Piper Navajo (PA-31)","ENR_AERONEF":"C-FPXL","TYPE_AERONEF":"Avion bimoteur","TAILLE_MO":"51.3","UUID":"f10c405ea1c849d093630d3a6988c163","NO_SEQ":871065,"PLUS_RECENTE":"Non","DATE_INDEX":"2026-03-07","product":"lidar","tile_id":"21_3114984F08_DB","url":"https://diffusion.mern.gouv.qc.ca/diffusion/RGQ/Lidar/2021_Monteregiesudest_Lidar_Den10_DonneesBrutes/Mtm8/Laz/21_3114984F08_DB.LAZ","provider":"QC"}},{"type":"Feature","geometry":{"type":"MultiPolygon","coordinates":[[[[-73.3579483934625,44.99589903392281,0],[-73.3579261051419,45.00489823241199,0],[-73.3706112508914,45.00491334523279,0],[-73.3706315434541,44.995914131579916,0],[-73.3579483934625,44.99589903392281,0]]]]},"properties":{"fid":624240,"NOM_TUILE":"21_3154984F08_DB","TELECHARGEMENT_TUILE":"https://diffusion.mern.gouv.qc.ca/diffusion/RGQ/Lidar/2021_Monteregiesudest_Lidar_Den10_DonneesBrutes/Mtm8/Laz/21_3154984F08_DB.LAZ","PROJET":"2021_Montérégie Sud-Est_Lidar","LICENCE":"Creative Commons Attribution 4.0 International (CC BY 4.0) https://www.donneesquebec.ca/licence","DROIT_AUTEUR":"© Gouvernement du Québec","TYPE_DONNEES":"Données brutes","DENSITE":"10 pts/m2","CLASSIFICATION":"0","PRECISION_PLANIMETRIQUE":"Approximative à 15 cm","PRECISION_ALTIMETRIQUE":"Approximative à 15 cm","PROJECTION":"MTM fuseau 8, NAD83 (SCRS)","SYSREF_ALTIMETRIQUE":"CGVD 1928","CODE_EPSG":"2950","FORMAT":"LAZ (Version 1.2)","DATES_ACQUISITION":"2021-10-23,2021-11-06","SAISONS":"Automne","SESSIONS_VOL":"21_600021-38_296-1,21_600021-38_310-2","CAPTEUR":"Optech ALTM Galaxy","TYPE_CAPTEUR":"LiDAR aéroporté","AERONEF":"Piper Navajo (PA-31)","ENR_AERONEF":"C-FPXL","TYPE_AERONEF":"Avion bimoteur","TAILLE_MO":"37.7","UUID":"bcf473961f2e492681019e1f0e57ac29","NO_SEQ":871197,"PLUS_RECENTE":"Non","DATE_INDEX":"2026-03-07","product":"lidar","tile_id":"21_3154984F08_DB","url":"https://diffusion.mern.gouv.qc.ca/diffusion/RGQ/Lidar/2021_Monteregiesudest_Lidar_Den10_DonneesBrutes/Mtm8/Laz/21_3154984F08_DB.LAZ","provider":"QC"}},{"type":"Feature","geometry":{"type":"MultiPolygon","coordinates":[[[[-73.4594137345772,44.99598019598363,0],[-73.4594074038034,45.00497941931219,0],[-73.4720926000292,45.00498320949419,0],[-73.47209693499721,44.99598397297121,0],[-73.4594137345772,44.99598019598363,0]]]]},"properties":{"fid":738527,"NOM_TUILE":"21_3074984F08_DB","TELECHARGEMENT_TUILE":"https://diffusion.mern.gouv.qc.ca/diffusion/RGQ/Lidar/2021_Monteregiesudest_Lidar_Den10_DonneesBrutes/Mtm8/Laz/21_3074984F08_DB.LAZ","PROJET":"2021_Montérégie Sud-Est_Lidar","LICENCE":"Creative Commons Attribution 4.0 International (CC BY 4.0) https://www.donneesquebec.ca/licence","DROIT_AUTEUR":"© Gouvernement du Québec","TYPE_DONNEES":"Données brutes","DENSITE":"10 pts/m2","CLASSIFICATION":"0","PRECISION_PLANIMETRIQUE":"Approximative à 15 cm","PRECISION_ALTIMETRIQUE":"Approximative à 15 cm","PROJECTION":"MTM fuseau 8, NAD83 (SCRS)","SYSREF_ALTIMETRIQUE":"CGVD 1928","CODE_EPSG":"2950","FORMAT":"LAZ (Version 1.2)","DATES_ACQUISITION":"2021-10-23,2021-11-06","SAISONS":"Automne","SESSIONS_VOL":"21_600021-38_296-1,21_600021-38_310-2","CAPTEUR":"Optech ALTM Galaxy","TYPE_CAPTEUR":"LiDAR aéroporté","AERONEF":"Piper Navajo (PA-31)","ENR_AERONEF":"C-FPXL","TYPE_AERONEF":"Avion bimoteur","TAILLE_MO":"50.5","UUID":"af5bb67dd9ff4dd994ad413a567e3c2e","NO_SEQ":870932,"PLUS_RECENTE":"Non","DATE_INDEX":"2026-03-07","product":"lidar","tile_id":"21_3074984F08_DB","url":"https://diffusion.mern.gouv.qc.ca/diffusion/RGQ/Lidar/2021_Monteregiesudest_Lidar_Den10_DonneesBrutes/Mtm8/Laz/21_3074984F08_DB.LAZ","provider":"QC"}},{"type":"Feature","geometry":{"type":"MultiPolygon","coordinates":[[[[-73.3833146504087,44.99592777166491,0],[-73.38329641674,45.004926997173094,0],[-73.3959815431829,45.0049392360855,0],[-73.3959978485305,44.995940037634526,0],[-73.3833146504087,44.99592777166491,0]]]]},"properties":{"fid":738551,"NOM_TUILE":"21_3134984F08_DB","TELECHARGEMENT_TUILE":"https://diffusion.mern.gouv.qc.ca/diffusion/RGQ/Lidar/2021_Monteregiesudest_Lidar_Den10_DonneesBrutes/Mtm8/Laz/21_3134984F08_DB.LAZ","PROJET":"2021_Montérégie Sud-Est_Lidar","LICENCE":"Creative Commons Attribution 4.0 International (CC BY 4.0) https://www.donneesquebec.ca/licence","DROIT_AUTEUR":"© Gouvernement du Québec","TYPE_DONNEES":"Données brutes","DENSITE":"10 pts/m2","CLASSIFICATION":"0","PRECISION_PLANIMETRIQUE":"Approximative à 15 cm","PRECISION_ALTIMETRIQUE":"Approximative à 15 cm","PROJECTION":"MTM fuseau 8, NAD83 (SCRS)","SYSREF_ALTIMETRIQUE":"CGVD 1928","CODE_EPSG":"2950","FORMAT":"LAZ (Version 1.2)","DATES_ACQUISITION":"2021-10-23,2021-11-06","SAISONS":"Automne","SESSIONS_VOL":"21_600021-38_296-1,21_600021-38_310-2","CAPTEUR":"Optech ALTM Galaxy","TYPE_CAPTEUR":"LiDAR aéroporté","AERONEF":"Piper Navajo (PA-31)","ENR_AERONEF":"C-FPXL","TYPE_AERONEF":"Avion bimoteur","TAILLE_MO":"55.9","UUID":"8bb904cea15243a5bed6b6a18ca48a39","NO_SEQ":871133,"PLUS_RECENTE":"Non","DATE_INDEX":"2026-03-07","product":"lidar","tile_id":"21_3134984F08_DB","url":"https://diffusion.mern.gouv.qc.ca/diffusion/RGQ/Lidar/2021_Monteregiesudest_Lidar_Den10_DonneesBrutes/Mtm8/Laz/21_3134984F08_DB.LAZ","provider":"QC"}},{"type":"Feature","geometry":{"type":"MultiPolygon","coordinates":[[[[-73.47209693499721,44.99598397297121,0],[-73.4720926000292,45.00498320949419,0],[-73.4847777522398,45.0049855866827,0],[-73.4847801589251,44.995986378871834,0],[-73.47209693499721,44.99598397297121,0]]]]},"properties":{"fid":852402,"NOM_TUILE":"21_3064984F08_DB","TELECHARGEMENT_TUILE":"https://diffusion.mern.gouv.qc.ca/diffusion/RGQ/Lidar/2021_Monteregiesudest_Lidar_Den10_DonneesBrutes/Mtm8/Laz/21_3064984F08_DB.LAZ","PROJET":"2021_Montérégie Sud-Est_Lidar","LICENCE":"Creative Commons Attribution 4.0 International (CC BY 4.0) https://www.donneesquebec.ca/licence","DROIT_AUTEUR":"© Gouvernement du Québec","TYPE_DONNEES":"Données brutes","DENSITE":"10 pts/m2","CLASSIFICATION":"0","PRECISION_PLANIMETRIQUE":"Approximative à 15 cm","PRECISION_ALTIMETRIQUE":"Approximative à 15 cm","PROJECTION":"MTM fuseau 8, NAD83 (SCRS)","SYSREF_ALTIMETRIQUE":"CGVD 1928","CODE_EPSG":"2950","FORMAT":"LAZ (Version 1.2)","DATES_ACQUISITION":"2021-10-23,2021-11-06","SAISONS":"Automne","SESSIONS_VOL":"21_600021-38_296-1,21_600021-38_310-2","CAPTEUR":"Optech ALTM Galaxy","TYPE_CAPTEUR":"LiDAR aéroporté","AERONEF":"Piper Navajo (PA-31)","ENR_AERONEF":"C-FPXL","TYPE_AERONEF":"Avion bimoteur","TAILLE_MO":"44.9","UUID":"64ad98b6b80f4a349b957fbc8eddb2c8","NO_SEQ":870899,"PLUS_RECENTE":"Non","DATE_INDEX":"2026-03-07","product":"lidar","tile_id":"21_3064984F08_DB","url":"https://diffusion.mern.gouv.qc.ca/diffusion/RGQ/Lidar/2021_Monteregiesudest_Lidar_Den10_DonneesBrutes/Mtm8/Laz/21_3064984F08_DB.LAZ","provider":"QC"}},{"type":"Feature","geometry":{"type":"MultiPolygon","coordinates":[[[[-73.51014812021,45.00498618229429,0],[-73.510146535276,44.99598694930742,0],[-73.4974633381992,44.99598737202502,0],[-73.4974629904474,45.004986589414294,0],[-73.51014812021,45.00498618229429,0]]]]},"properties":{"fid":852439,"NOM_TUILE":"21_3044984F08_DB","TELECHARGEMENT_TUILE":"https://diffusion.mern.gouv.qc.ca/diffusion/RGQ/Lidar/2021_Monteregiesudest_Lidar_Den10_DonneesBrutes/Mtm8/Laz/21_3044984F08_DB.LAZ","PROJET":"2021_Montérégie Sud-Est_Lidar","LICENCE":"Creative Commons Attribution 4.0 International (CC BY 4.0) https://www.donneesquebec.ca/licence","DROIT_AUTEUR":"© Gouvernement du Québec","TYPE_DONNEES":"Données brutes","DENSITE":"10 pts/m2","CLASSIFICATION":"0","PRECISION_PLANIMETRIQUE":"Approximative à 15 cm","PRECISION_ALTIMETRIQUE":"Approximative à 15 cm","PROJECTION":"MTM fuseau 8, NAD83 (SCRS)","SYSREF_ALTIMETRIQUE":"CGVD 1928","CODE_EPSG":"2950","FORMAT":"LAZ (Version 1.2)","DATES_ACQUISITION":"2021-10-23,2021-11-06","SAISONS":"Automne","SESSIONS_VOL":"21_600021-38_296-1,21_600021-38_310-2","CAPTEUR":"Optech ALTM Galaxy","TYPE_CAPTEUR":"LiDAR aéroporté","AERONEF":"Piper Navajo (PA-31)","ENR_AERONEF":"C-FPXL","TYPE_AERONEF":"Avion bimoteur","TAILLE_MO":"36.3","UUID":"a2c44d406b8f46c08f4568507950da1c","NO_SEQ":870835,"PLUS_RECENTE":"Non","DATE_INDEX":"2026-03-07","product":"lidar","tile_id":"21_3044984F08_DB","url":"https://diffusion.mern.gouv.qc.ca/diffusion/RGQ/Lidar/2021_Monteregiesudest_Lidar_Den10_DonneesBrutes/Mtm8/Laz/21_3044984F08_DB.LAZ","provider":"QC"}}]}